[
    {
      "id": 1,
      "name": "Dr. Anika Sharma",
      "expertise": "Orthopedic Physiotherapy",
      "city": "Mumbai"
    },
    {
      "id": 2,
      "name": "Dr. Raj Singh",
      "expertise": "Neurological Physiotherapy",
      "city": "Delhi"
    },
    {
      "id": 3,
      "name": "Dr. Priya Verma",
      "expertise": "Cardiopulmonary Physiotherapy",
      "city": "Bangalore"
    },
    {
      "id": 4,
      "name": "Dr. Arjun Gupta",
      "expertise": "Sports Physiotherapy",
      "city": "Chennai"
    },
    {
      "id": 5,
      "name": "Dr. Nisha Patel",
      "expertise": "Pediatric Physiotherapy",
      "city": "Hyderabad"
    },
    {
      "id": 6,
      "name": "Dr. Rohit Sharma",
      "expertise": "Geriatric Physiotherapy",
      "city": "Kolkata"
    },
    {
      "id": 7,
      "name": "Dr. Pooja Malhotra",
      "expertise": "Orthopedic Physiotherapy",
      "city": "Ahmedabad"
    },
    {
      "id": 8,
      "name": "Dr. Siddharth Reddy",
      "expertise": "Neurological Physiotherapy",
      "city": "Pune"
    },
    {
      "id": 9,
      "name": "Dr. Aisha Khan",
      "expertise": "Cardiopulmonary Physiotherapy",
      "city": "Jaipur"
    },
    {
      "id": 10,
      "name": "Dr. Sameer Kumar",
      "expertise": "Sports Physiotherapy",
      "city": "Lucknow"
    },
    {
      "id": 11,
      "name": "Dr. Ananya Gupta",
      "expertise": "Pediatric Physiotherapy",
      "city": "Chandigarh"
    },
    {
      "id": 12,
      "name": "Dr. Rahul Singh",
      "expertise": "Geriatric Physiotherapy",
      "city": "Bhopal"
    },
    {
      "id": 13,
      "name": "Dr. Ritu Sharma",
      "expertise": "Orthopedic Physiotherapy",
      "city": "Indore"
    },
    {
      "id": 14,
      "name": "Dr. Kartik Mehta",
      "expertise": "Neurological Physiotherapy",
      "city": "Nagpur"
    },
    {
      "id": 15,
      "name": "Dr. Aarohi Patel",
      "expertise": "Cardiopulmonary Physiotherapy",
      "city": "Surat"
    },
    {
      "id": 16,
      "name": "Dr. Sanjay Kumar",
      "expertise": "Sports Physiotherapy",
      "city": "Ahmednagar"
    },
    {
      "id": 17,
      "name": "Dr. Riya Singh",
      "expertise": "Pediatric Physiotherapy",
      "city": "Agra"
    },
    {
      "id": 18,
      "name": "Dr. Varun Gupta",
      "expertise": "Geriatric Physiotherapy",
      "city": "Coimbatore"
    },
    {
      "id": 19,
      "name": "Dr. Shreya Mishra",
      "expertise": "Orthopedic Physiotherapy",
      "city": "Goa"
    },
    {
      "id": 20,
      "name": "Dr. Manoj Reddy",
      "expertise": "Neurological Physiotherapy",
      "city": "Vadodara"
    },
    {
      "id": 21,
      "name": "Dr. Naina Verma",
      "expertise": "Cardiopulmonary Physiotherapy",
      "city": "Ludhiana"
    },
    {
      "id": 22,
      "name": "Dr. Aditya Jain",
      "expertise": "Sports Physiotherapy",
      "city": "Jodhpur"
    },
    {
      "id": 23,
      "name": "Dr. Priyanka Singh",
      "expertise": "Pediatric Physiotherapy",
      "city": "Kanpur"
    },
    {
      "id": 24,
      "name": "Dr. Akshay Patel",
      "expertise": "Geriatric Physiotherapy",
      "city": "Ranchi"
    },
    {
      "id": 25,
      "name": "Dr. Anjali Sharma",
      "expertise": "Orthopedic Physiotherapy",
      "city": "Patna"
    },
    {
      "id": 26,
      "name": "Dr. Rohan Gupta",
      "expertise": "Neurological Physiotherapy",
      "city": "Kochi"
    },
    {
      "id": 27,
      "name": "Dr. Sneha Verma",
      "expertise": "Cardiopulmonary Physiotherapy",
      "city": "Mysore"
    },
    {
      "id": 28,
      "name": "Dr. Vikrant Reddy",
      "expertise": "Sports Physiotherapy",
      "city": "Visakhapatnam"
    },
    {
      "id": 29,
      "name": "Dr. Aanya Kapoor",
      "expertise": "Pediatric Physiotherapy",
      "city": "Nashik"
    },
    {
      "id": 30,
      "name": "Dr. Rohit Singh",
      "expertise": "Geriatric Physiotherapy",
      "city": "Amritsar"
    }
  ]
